pyfortunecookie/__init__.py
pyfortunecookie/__main__.py
pyfortunecookie/core.py
pyfortunecookie_teammeridian-0.1.5.dist-info/licenses/LICENSE
pyfortunecookie_teammeridian-0.1.5.dist-info/METADATA
pyfortunecookie_teammeridian-0.1.5.dist-info/WHEEL
pyfortunecookie_teammeridian-0.1.5.dist-info/entry_points.txt
pyfortunecookie_teammeridian-0.1.5.dist-info/top_level.txt
pyfortunecookie_teammeridian-0.1.5.dist-info/RECORD
