Metadata-Version: 2.4
Name: pyfortunecookie-teammeridian
Version: 0.1.5
Summary: A fun fortune cookie generator with lucky number and color
Author-email: SinaL0123 <sl9608@nyu.edu>, DplayerXAX <danielhuang0905@outlook.com>, aayanmathur <am12611@nyu.edu>, TogawaSaki0214 <hc3311@nyu.edu>, amendahawi <am13948@nyu.edu>
License:                     GNU GENERAL PUBLIC LICENSE
Project-URL: Homepage, https://github.com/swe-students-fall2025/3-python-package-team_meridian
Project-URL: Repository, https://github.com/swe-students-fall2025/3-python-package-team_meridian.git
Project-URL: Bug Tracker, https://github.com/swe-students-fall2025/3-python-package-team_meridian/issues
Keywords: fortune,fun,demo
Classifier: Programming Language :: Python :: 3
Classifier: Intended Audience :: Education
Classifier: License :: OSI Approved :: GNU General Public License v3 (GPLv3)
Classifier: Operating System :: OS Independent
Requires-Python: >=3.7
License-File: LICENSE
Provides-Extra: dev
Requires-Dist: pytest; extra == "dev"
Dynamic: license-file
